src/__init__.py
src/random.py
src/run_cifar.py
test_pytorch_gpu-0.0.4.dist-info/LICENSE
test_pytorch_gpu-0.0.4.dist-info/METADATA
test_pytorch_gpu-0.0.4.dist-info/WHEEL
test_pytorch_gpu-0.0.4.dist-info/entry_points.txt
test_pytorch_gpu-0.0.4.dist-info/top_level.txt
test_pytorch_gpu-0.0.4.dist-info/RECORD
