Metadata-Version: 2.1
Name: test-pytorch-gpu
Version: 0.0.4
Summary: Check pytorch + GPU is setted up
Home-page: https://github.com/ademyanchuk/test_pytorch_gpu
Author: Alexey Demyanchuk
Author-email: alexeydemyanchuk@gmail.com
License: MIT License
Keywords: pytorch,GPU,test setup
Platform: UNKNOWN
Classifier: Development Status :: 3 - Alpha
Classifier: Intended Audience :: Developers
Classifier: Topic :: Software Development :: Build Tools
Classifier: License :: OSI Approved :: MIT License
Classifier: Natural Language :: English
Classifier: Programming Language :: Python :: 3
Requires-Python: >=3.8
License-File: LICENSE
Requires-Dist: torch (>=1.9.0)
Requires-Dist: torchvision (>=0.10.0)
Provides-Extra: dev
Requires-Dist: black (>=21.5b) ; extra == 'dev'
Requires-Dist: flake8 (>=3.9) ; extra == 'dev'
Requires-Dist: isort (>=5.9) ; extra == 'dev'
